{
  "kind": "collectionType",
  "collectionName": "categories",
  "info": {
    "singularName": "category",
    "pluralName": "categories",
    "displayName": "category"
  },
  "options": {
    "draftAndPublish": true
  },
  "pluginOptions": {},
  "attributes": {
    "id_categoria": {
      "type": "uid"
    },
    "nombre": {
      "type": "string"
    },
    "contenido": {
      "allowedTypes": [
        "images",
        "files",
        "videos",
        "audios"
      ],
      "type": "media",
      "multiple": true
    }
  }
}
